mft2es/__init__.py
mft2es/models/ElasticsearchUtils.py
mft2es/models/MetaData.py
mft2es/models/Mft2es.py
mft2es/presenters/Mft2esPresenter.py
mft2es/presenters/Mft2jsonPresenter.py
mft2es/views/BaseView.py
mft2es/views/Mft2esView.py
mft2es/views/Mft2jsonView.py
mft2es-1.7.2.dist-info/METADATA
mft2es-1.7.2.dist-info/WHEEL
mft2es-1.7.2.dist-info/entry_points.txt
mft2es-1.7.2.dist-info/licenses/LICENSE
mft2es-1.7.2.dist-info/RECORD
