Metadata-Version: 2.4
Name: mft2es
Version: 1.7.2
Summary: A library for fast import of Windows Master File Table($MFT) into Elasticsearch.
Author-email: sumeshi <sum3sh1@protonmail.com>
License-Expression: MIT
License-File: LICENSE
Requires-Python: >=3.11
Requires-Dist: elasticsearch>=9.0.2
Requires-Dist: mft>=0.6.1
Requires-Dist: orjson>=3.10.18
Requires-Dist: tqdm>=4.67.1
Requires-Dist: urllib3>=2.4.0
